co2tools/__init__.py
co2tools/__version__.py
co2tools/build.py
co2tools/mergers/__init__.py
co2tools/mergers/dxf.py
co2tools/stl/__init__.py
co2tools/stl/builder.py
co2tools-0.0.2.24.data/scripts/co2tools
co2tools-0.0.2.24.dist-info/LICENSE
co2tools-0.0.2.24.dist-info/METADATA
co2tools-0.0.2.24.dist-info/WHEEL
co2tools-0.0.2.24.dist-info/entry_points.txt
co2tools-0.0.2.24.dist-info/top_level.txt
co2tools-0.0.2.24.dist-info/RECORD
