Metadata-Version: 2.1
Name: co2tools
Version: 0.0.2.24
Summary: Easily automate generating 3D models from DXF files and merge DXF files for CO2 laser cutting
Home-page: https://github.com/Mambix/co2tools
Author: Mambix Ltd.
Author-email: ledi.mambix@gmail.com
License: MIT
Platform: UNKNOWN
Classifier: Development Status :: 2 - Pre-Alpha
Classifier: Topic :: Multimedia :: Graphics :: 3D Modeling
Classifier: License :: OSI Approved :: MIT License
Classifier: Programming Language :: Python
Classifier: Programming Language :: Python :: 3.4
Classifier: Programming Language :: Python :: 3.5
Requires-Dist: numpy
Requires-Dist: scipy
Requires-Dist: trimesh[easy]
Requires-Dist: ezdxf
Requires-Dist: networkx
Requires-Dist: PyYaml
